{
  "db_name": "PostgreSQL",
  "query": "\n        SELECT id, name, sku, stock, minimun, maximun, created_at, updated_at, status FROM inventory WHERE status != false\n        ",
  "describe": {
    "columns": [
      {
        "ordinal": 0,
        "name": "id",
        "type_info": "Int4"
      },
      {
        "ordinal": 1,
        "name": "name",
        "type_info": "Varchar"
      },
      {
        "ordinal": 2,
        "name": "sku",
        "type_info": "Varchar"
      },
      {
        "ordinal": 3,
        "name": "stock",
        "type_info": "Int4"
      },
      {
        "ordinal": 4,
        "name": "minimun",
        "type_info": "Int4"
      },
      {
        "ordinal": 5,
        "name": "maximun",
        "type_info": "Int8"
      },
      {
        "ordinal": 6,
        "name": "created_at",
        "type_info": "Timestamptz"
      },
      {
        "ordinal": 7,
        "name": "updated_at",
        "type_info": "Timestamptz"
      },
      {
        "ordinal": 8,
        "name": "status",
        "type_info": "Bool"
      }
    ],
    "parameters": {
      "Left": []
    },
    "nullable": [
      false,
      false,
      false,
      false,
      false,
      false,
      false,
      false,
      false
    ]
  },
  "hash": "d4598df5e13b3bd8a8b92b658adc50d78a720cf9ce76c7da355a9543e7565bab"
}
